tmdbv3api/__init__.py
tmdbv3api/as_obj.py
tmdbv3api/exceptions.py
tmdbv3api/tmdb.py
tmdbv3api/objs/__init__.py
tmdbv3api/objs/account.py
tmdbv3api/objs/auth.py
tmdbv3api/objs/certification.py
tmdbv3api/objs/change.py
tmdbv3api/objs/collection.py
tmdbv3api/objs/company.py
tmdbv3api/objs/configuration.py
tmdbv3api/objs/credit.py
tmdbv3api/objs/discover.py
tmdbv3api/objs/episode.py
tmdbv3api/objs/find.py
tmdbv3api/objs/genre.py
tmdbv3api/objs/group.py
tmdbv3api/objs/keyword.py
tmdbv3api/objs/list.py
tmdbv3api/objs/movie.py
tmdbv3api/objs/network.py
tmdbv3api/objs/person.py
tmdbv3api/objs/provider.py
tmdbv3api/objs/review.py
tmdbv3api/objs/search.py
tmdbv3api/objs/season.py
tmdbv3api/objs/trending.py
tmdbv3api/objs/tv.py
tmdbv3api-1.9.0.dist-info/METADATA
tmdbv3api-1.9.0.dist-info/WHEEL
tmdbv3api-1.9.0.dist-info/top_level.txt
tmdbv3api-1.9.0.dist-info/RECORD
