Metadata-Version: 2.1
Name: tmdbv3api
Version: 1.9.0
Summary: A lightweight Python library for The Movie Database (TMDb) API.
Home-page: https://github.com/AnthonyBloomer/tmdbv3api
Author: Anthony Bloomer
Author-email: ant0@protonmail.ch
License: MIT
Keywords: movie,tvmovie database,tmdb,wrapper,database,themoviedb,moviedb,api
Classifier: Development Status :: 5 - Production/Stable
Classifier: Intended Audience :: Developers
Classifier: Topic :: Software Development :: Libraries
Classifier: Programming Language :: Python
Classifier: Programming Language :: Python :: 2.7
Classifier: Programming Language :: Python :: 3
Classifier: Programming Language :: Python :: 3.3
Classifier: Programming Language :: Python :: 3.4
Classifier: Programming Language :: Python :: 3.5
Classifier: Programming Language :: Python :: 3.6
Classifier: Programming Language :: Python :: 3.7
Classifier: Programming Language :: Python :: 3.8
